<?xml version="1.0" encoding="utf-8"?>
<!DOCTYPE hibernate-mapping PUBLIC "-//Hibernate/Hibernate Mapping DTD 3.0//EN"
"http://hibernate.sourceforge.net/hibernate-mapping-3.0.dtd">
<!-- 
    Mapping file autogenerated by MyEclipse Persistence Tools
-->
<hibernate-mapping>
    <class name="com.fdo.hum.UserMusicClassify" table="user_music_classify" catalog="hnmusic_telecom2">
        <id name="id" type="java.lang.Integer">
            <column name="id" />
            <generator class="identity" />
        </id>
        <property name="userId" type="java.lang.String">
            <column name="userId" length="20">
                <comment>用户id</comment>
            </column>
        </property>
        <property name="musicId" type="java.lang.Integer">
            <column name="musicId" not-null="true">
                <comment>音乐Id</comment>
            </column>
        </property>
        <property name="createDateTime" type="java.sql.Timestamp">
            <column name="createDateTime" length="19">
                <comment>创建时间</comment>
            </column>
        </property>
        <property name="updateDateTime" type="java.sql.Timestamp">
            <column name="updateDateTime" length="19">
                <comment>更新时间</comment>
            </column>
        </property>
        <property name="isuse" type="java.lang.Integer">
            <column name="isuse">
                <comment>是否在收藏 0：在收藏 1：取消收藏</comment>
            </column>
        </property>
        <property name="type" type="java.lang.Integer">
            <column name="type">
                <comment>0是音乐 1是视频</comment>
            </column>
        </property>
    </class>
</hibernate-mapping>
